[
  {
    "label": "What is the name of Morty's crush at his high school?",
    "choices": [
      {
        "value": "Julia",
        "correct": false
      },
      {
        "value": "Jenny",
        "correct": false
      },
      {
        "value": "Joanna",
        "correct": false
      },
      {
        "value": "Jessica",
        "correct": true
      }
    ]
  },
  {
    "label": "What is 'Morty' short for?",
    "choices": [
      {
        "value": "Mortisson",
        "correct": false
      },
      {
        "value": "Mortell",
        "correct": false
      },
      {
        "value": "Morton",
        "correct": false
      },
      {
        "value": "Mortimer",
        "correct": true
      }
    ]
  },
  {
    "label": "Who is the rapper on the poster in Summer's room?",
    "choices": [
      {
        "value": "Biggie Smalls",
        "correct": false
      },
      {
        "value": "Tupac Shakur",
        "correct": true
      },
      {
        "value": "Enimem",
        "correct": false
      },
      {
        "value": "Snoop Dogg",
        "correct": false
      }
    ]
  },
  {
    "label": "What is Beth's Job?",
    "choices": [
      {
        "value": "Mouse Catcher",
        "correct": false
      },
      {
        "value": "Dog Whisperer",
        "correct": false
      },
      {
        "value": "Horse Veterinarian",
        "correct": true
      },
      {
        "value": "Cat Show Host",
        "correct": false
      }
    ]
  },
  {
    "label": "The clock in Rick's garage always shows Two o'clock except in one episode. What time does the clock show in that episode?",
    "choices": [
      {
        "value": "Three o'clock",
        "correct": true
      },
      {
        "value": "Five o'clock",
        "correct": false
      },
      {
        "value": "Twelve o'clock",
        "correct": false
      },
      {
        "value": "Ten o'clock",
        "correct": false
      }
    ]
  },
  {
    "label": "In the episode Meeseeks and Destroy, what does Jerry want help improving?",
    "choices": [
      {
        "value": "Swimming",
        "correct": false
      },
      {
        "value": "Golf",
        "correct": true
      },
      {
        "value": "Social Events",
        "correct": false
      },
      {
        "value": "Dating",
        "correct": false
      }
    ]
  }
]